clf/__init__.py
clf/classifier.py
demo/__init__.py
demo/demo4.py
format/__init__.py
format/converter.py
rusentiment-0.0.2.dist-info/DESCRIPTION.rst
rusentiment-0.0.2.dist-info/METADATA
rusentiment-0.0.2.dist-info/RECORD
rusentiment-0.0.2.dist-info/WHEEL
rusentiment-0.0.2.dist-info/entry_points.txt
rusentiment-0.0.2.dist-info/metadata.json
rusentiment-0.0.2.dist-info/top_level.txt
syntax/__init__.py
syntax/maltparser/__init__.py
syntax/maltparser/dependencygraph.py
syntax/maltparser/malt.py
