Metadata-Version: 2.0
Name: rusentiment
Version: 0.0.2
Summary: Sentiment analysis library based on machine learning methods
Home-page: https://github.com/Smeta/rusentiment
Author: Sergey Smetanin
Author-email: sismetanin@gmail.com
License: MIT
Download-URL: https://github.com/Smeta/rusentiment/tarball/0.0.2
Keywords: russian text analysis,sentiment analysis,syntactic features
Platform: UNKNOWN
Requires-Dist: numpy (>=1.7.1)
